mort/__init__.py
mort/__main__.py
mort/mort.py
mort-0.9.1.dist-info/METADATA
mort-0.9.1.dist-info/RECORD
mort-0.9.1.dist-info/WHEEL
mort-0.9.1.dist-info/entry_points.txt
mort-0.9.1.dist-info/top_level.txt
mort-0.9.1.dist-info/zip-safe
